evolutionary_algorithm/__init__.py
evolutionary_algorithm/main.py
evolutionary_algorithm-0.0.2.dist-info/LICENSE
evolutionary_algorithm-0.0.2.dist-info/METADATA
evolutionary_algorithm-0.0.2.dist-info/WHEEL
evolutionary_algorithm-0.0.2.dist-info/top_level.txt
evolutionary_algorithm-0.0.2.dist-info/RECORD
