Metadata-Version: 2.1
Name: evolutionary-algorithm
Version: 0.0.2
Summary: An evolutionary (genetic) algorithm designed specifically for optimizing predictive models with integer, real, boolean, and categorical inputs.
Home-page: https://github.com/dmartintucker/evolutionary-algorithm
Author: Daniel Tucker
Author-email: dmartintucker@gmail.com
Maintainer: Daniel Tucker
License: UNKNOWN
Keywords: Python,evolutionary,genetic,algorithm,GA
Platform: UNKNOWN
Classifier: Programming Language :: Python :: 3
Classifier: License :: OSI Approved :: MIT License
Classifier: Operating System :: OS Independent
Classifier: Topic :: Software Development :: Libraries :: Python Modules
Requires-Python: >3.6
Requires-Dist: func-timeout
Requires-Dist: numpy
